MANIFEST.in
README.md
VERSION
setup.py
hitchqs/__init__.py
hitchqs/commandline.py
hitchqs.egg-info/PKG-INFO
hitchqs.egg-info/SOURCES.txt
hitchqs.egg-info/dependency_links.txt
hitchqs.egg-info/entry_points.txt
hitchqs.egg-info/not-zip-safe
hitchqs.egg-info/requires.txt
hitchqs.egg-info/top_level.txt
hitchqs/demo/hitchstory/engine.py
hitchqs/demo/hitchstory/hitchqs.yml
hitchqs/demo/hitchstory/hitchreqs.in
hitchqs/demo/hitchstory/key.py
hitchqs/demo/hitchstory/mystory.story
hitchqs/demo/key/hitchqs.yml
hitchqs/demo/key/hitchreqs.in
hitchqs/demo/key/key.py
hitchqs/demo/pythonapi/game.py
hitchqs/demo/pythonapi/hitchqs.yml
hitchqs/demo/pythonapi/requirements.txt
hitchqs/demo/pythonapi/state.py
hitchqs/demo/pythonapi/hitch/engine.py
hitchqs/demo/pythonapi/hitch/hitchreqs.in
hitchqs/demo/pythonapi/hitch/key.py
hitchqs/demo/pythonapi/hitch/__pycache__/engine.cpython-38.pyc
hitchqs/demo/pythonapi/hitch/__pycache__/key.cpython-38.pyc
hitchqs/demo/pythonapi/story/glider.story
hitchqs/demo/seleniumdirector/engine.py
hitchqs/demo/seleniumdirector/hitchqs.yml
hitchqs/demo/seleniumdirector/hitchreqs.in
hitchqs/demo/seleniumdirector/key.py
hitchqs/demo/seleniumdirector/mystory.story
hitchqs/demo/seleniumdirector/selectors.yml
hitchqs/skeleton/hitchpylibrary/MANIFEST.in
hitchqs/skeleton/hitchpylibrary/README.md
hitchqs/skeleton/hitchpylibrary/VERSION
hitchqs/skeleton/hitchpylibrary/hitchqs.yml
hitchqs/skeleton/hitchpylibrary/setup.py
hitchqs/skeleton/hitchpylibrary/hitch/build.py
hitchqs/skeleton/hitchpylibrary/hitch/debugrequirements.txt
hitchqs/skeleton/hitchpylibrary/hitch/engine.py
hitchqs/skeleton/hitchpylibrary/hitch/hitchreqs.in
hitchqs/skeleton/hitchpylibrary/hitch/key.py
hitchqs/skeleton/hitchpylibrary/hitch/story/example.story
hitchqs/skeleton/hitchstory/engine.py
hitchqs/skeleton/hitchstory/hitchqs.yml
hitchqs/skeleton/hitchstory/hitchreqs.in
hitchqs/skeleton/hitchstory/key.py
hitchqs/skeleton/hitchstory/mystory.story
hitchqs/skeleton/key/hitchqs.yml
hitchqs/skeleton/key/hitchreqs.in
hitchqs/skeleton/key/key.py